Metadata-Version: 2.4
Name: iflow-mcp_jordyzomer_codeql-mcp
Version: 1.0.0
Summary: A Model Context Protocol (MCP) server that wraps the CodeQL query server
Requires-Python: >=3.8
Requires-Dist: fastmcp>=0.1.0
Requires-Dist: httpx>=0.24.0
